excelipy/__init__.py
excelipy/const.py
excelipy/models.py
excelipy/service.py
excelipy/style.py
excelipy/styles/__init__.py
excelipy/styles/link.py
excelipy/styles/table.py
excelipy/styles/text.py
excelipy/writers/__init__.py
excelipy/writers/fill.py
excelipy/writers/image.py
excelipy/writers/link.py
excelipy/writers/table.py
excelipy/writers/text.py
excelipy-1.0.1.dist-info/METADATA
excelipy-1.0.1.dist-info/WHEEL
excelipy-1.0.1.dist-info/top_level.txt
excelipy-1.0.1.dist-info/RECORD
