Metadata-Version: 2.4
Name: excelipy
Version: 1.0.1
Summary: Wrapper around xlsxwriter to improve usability
Requires-Python: >=3.9.10
Requires-Dist: numpy>=2.0.2
Requires-Dist: pandas>=2.2.3
Requires-Dist: pillow>=11.3.0
Requires-Dist: pydantic>=2.11.3
Requires-Dist: xlsxwriter>=3.2.2
